Kool-0.0.2.dist-info/DESCRIPTION.rst
Kool-0.0.2.dist-info/METADATA
Kool-0.0.2.dist-info/RECORD
Kool-0.0.2.dist-info/WHEEL
Kool-0.0.2.dist-info/metadata.json
Kool-0.0.2.dist-info/top_level.txt
kool/__init__.py
kool/contrib/__init__.py
kool/contrib/auth/__init__.py
kool/contrib/auth/group.py
kool/contrib/auth/hasher.py
kool/contrib/auth/permission.py
kool/contrib/auth/user.py
kool/contrib/courses/__init__.py
kool/contrib/courses/course.py
kool/contrib/quizzes/__init__.py
kool/contrib/quizzes/question.py
kool/contrib/quizzes/quiz.py
kool/core/__init__.py
kool/core/exceptions.py
kool/core/handlers/__init__.py
kool/db/__init__.py
kool/db/models.py
kool/db/flatfile/__init__.py
kool/db/flatfile/database.py
kool/db/flatfile/queries.py
kool/db/flatfile/storages.py
kool/db/flatfile/utils.py
kool/utils/__init__.py
kool/utils/converter.py
kool/utils/crypto.py
kool/utils/encoding.py
kool/utils/timezone.py
tests/__init__.py
tests/contrib/__init__.py
tests/contrib/auth/__init__.py
tests/contrib/auth/test_user.py
tests/contrib/quizzes/__init__.py
tests/contrib/quizzes/test_question.py
tests/contrib/quizzes/test_quiz.py
tests/db/__init__.py
tests/db/flatfile/__init__.py
tests/db/flatfile/test_database.py
tests/db/flatfile/test_queries.py
tests/db/flatfile/test_storages.py
