Metadata-Version: 2.0
Name: Kool
Version: 0.0.2
Summary: Kool is an open source platform for online classroom management. 
Home-page: https://github.com/edasi/kool
Author: Antony Orenge
Author-email: orenge@ut.ee
License: MIT
Keywords: education learning database nosql
Platform: UNKNOWN
Classifier: Development Status :: 5 - Production/Stable
Classifier: Intended Audience :: Developers
Classifier: License :: OSI Approved :: MIT License
Classifier: Topic :: Education
Classifier: Programming Language :: Python :: 3.3
Classifier: Programming Language :: Python :: 3.4
Classifier: Programming Language :: Python :: 3.5
Classifier: Programming Language :: Python :: 3.6
Classifier: Programming Language :: Python :: Implementation :: PyPy
Classifier: Operating System :: OS Independent
Requires-Python: >=3
